{
	/* COLOR KEY

	 DARK BACKGROUND
	 #181A1B : background dark
	 #242627 : background medium (old: #222022, #191819)
	 #37393A : background light (old: #493441)
	 
	 LIGHT FOREGROUND
	 #CDBD96 : foreground back
	 #CDBD96 : foreground middle
	 #DBD6D5 : foreground front (old: #726472)
	 
	 ACCENT 1 - YELLOW
	 #CC960C : accent 1 back
	 #F9B70E : accent 1 middle
	 #FAC439 : accent 1 front

	 ACCENT 2 - ORANGE
	 #B96A23 : accent 2 back
	 #E2812A : accent 2 middle (old: #806292)
	 #E79750 : accent 2 front (old: #e2312a)
	 
	 ACCENT 3 - RED-ORANGE
	 #B04025 : accent 3 back (old: #D64E2C)
	 #D64E2C : accent 3 middle (old: #794966)
	 #DD6E52 : accent 3 front (old: #a1495c)
	 
	 ACCENT 4 - GREEN
	 #3C7140 : accent 4 back
	 #58A75E : accent 4 middle
	 #76B77B : accent 4 front

	 #ce3e4a : error (old: #D64E2C)
	 */
	"name": "samus",
	"type": "dark",
	"colors": {
		"foreground": "#CDBD96",

		//"selection.background": "#F9B70E",

		"scrollbar.shadow": "#ffffff00",
		"scrollbarSlider.background": "#ffffff18",

		"progressBar.background": "#B04025",

		"titleBar.activeBackground": "#242627",
		"titleBar.activeForeground": "#CDBD9688",
		"titleBar.inactiveBackground": "#242627",

		"statusBar.debuggingBackground": "#D64E2C",
		"statusBar.foreground": "#CDBD96",
		"statusBar.background": "#ffffff11",
		"statusBar.border": "#ffffff11",

		"editorCursor.foreground": "#CDBD96",
		"editor.background": "#181a1b",
		"editor.foreground": "#CDBD96",
		"editorGroupHeader.tabsBackground": "#242627",
		"editorWidget.background": "#242627",
		"editorWidget.border": "#D64E2C",
		"editor.selectionBackground": "#E2812A55",
		"editor.inactiveSelectionBackground": "#834a1855",
		
		"editor.selectionHighlightBackground": "#E2812A28",
		//"editor.selectionHighlightBorder": "#00000000",

		"editor.findMatchBackground": "#E2812A28",
		"editor.findMatchBorder": "#E2812A",
		
		"editor.findMatchHighlightBackground": "#c6496430",
		"editor.hoverHighlightBackground": "#ffffff11",
		"editorOverviewRuler.findMatchForeground": "#CDBD9688",
		"editor.lineHighlightBackground": "#ffffff04",
		"editorWhitespace.foreground": "#363036",
		"editorIndentGuide.background": "#272427",
		"editorIndentGuide.activeBackground": "#ffffff11",
		"editorLineNumber.foreground": "#CDBD9644",
		"editorLineNumber.activeForeground": "#DD6E52",
		"editorRuler.foreground": "#49343d",
		"editorBracketMatch.background": "#CDBD9622",
		"editorBracketMatch.border": "#00000000",
		"editorOverviewRuler.border": "#242627",
		"editorError.foreground": "#D64E2C",
		"editorWarning.foreground": "#d16d8a",
		"editorInfo.foreground": "#E79750",
		"editorHint.foreground": "#58A75E",
		"editorGutter.modifiedBackground": "#E79750",
		"editorGutter.addedBackground": "#58A75E",
		"editorGutter.deletedBackground": "#D64E2C",

		"focusBorder": "#E2812A",

		"sideBar.border": "#181a1b",
		//"sideBarSectionHeader.border": "#00ff00",

		"tab.activeBackground": "#181A1B",
		"tab.activeForeground": "#CDBD96",
		"tab.inactiveBackground": "#242627",
		"tab.inactiveForeground": "#CDBD9688",
		"tab.border": "#181A1B",

		"panel.background": "#242627",
		"panel.border": "#242627",
		"panelTitle.activeForeground": "#E79750",
		"panelTitle.inactiveForeground": "#CDBD9688",

		"activityBar.background": "#242627",
		"activityBar.foreground": "#E79750",
		"activityBarBadge.background": "#D64E2C",
		"activityBarBadge.foreground": "#CDBD96",

		"sideBar.background": "#242627",
		"sideBarTitle.foreground": "#CDBD9644",
		"sideBarSectionHeader.background": "#E2812A",
		"sideBarSectionHeader.foreground": "#242627",

		"terminal.foreground": "#CDBD96",
		"terminalCursor.foreground": "#CDBD96",
		"terminal.selectionBackground": "#141114",

		"textLink.foreground": "#E79750",
		"textLink.activeForeground": "#D64E2C",

		"widget.shadow": "#00000066",

		"input.background": "#242627",
		"input.foreground": "#CDBD96",
		"input.border": "#E79750",
		"input.placeholderForeground": "#CDBD9644",
		//"inputOption.activeBorder": "#ff0000",
		"inputValidation.errorBackground": "#D64E2C44",
		"inputValidation.errorBorder": "#D64E2C",

		"dropdown.background": "#242627",
		"dropdown.foreground": "#CDBD96",

		"list.focusBackground": "#ffffff11",
		"list.activeSelectionBackground": "#242627",
		"list.activeSelectionForeground": "#CDBD96",
		"list.inactiveSelectionBackground": "#242627",
		"list.inactiveSelectionForeground": "#CDBD96",
		"list.inactiveFocusBackground": "#ffffff11",
		"list.hoverBackground": "#ffffff11",
		"list.dropBackground": "#383b3d",
		"list.errorForeground": "#D64E2C",
		"list.warningForeground": "#E79750",

		"pickerGroup.foreground": "#E79750",
		"pickerGroup.border": "#ffffff11",

		"button.background": "#B04025",
		"button.foreground": "#CDBD96",

		"badge.background": "#B04025",
		"badge.foreground": "#CDBD96",

		"diffEditor.insertedTextBackground": "#02f79922",
		"diffEditor.removedTextBackground": "#D64E2C55",

		"peekViewTitle.background": "#E2812A",
		"peekViewTitleLabel.foreground": "#242627",
		"peekViewTitleDescription.foreground": "#242627",
		"peekView.border": "#E2812A",
		"peekViewResult.background": "#ffffff22",
		//"peekViewResult.lineForeground": "#ff0000",
		"peekViewResult.selectionBackground": "#242627",
		"peekViewResult.selectionForeground": "#CDBD96",
		"peekViewEditor.background": "#242627",
		//"peekViewResult.matchHighlightBackground": "#ffffff33",
		//"peekViewEditor.matchHighlightBackground": "#ffffff33",
		//"peekViewResult.fileForeground": "#ff0000",
		//"peekViewEditor.matchHighlightBorder": "#B04025",

		"notifications.background": "#242627",

		

		"debugToolBar.background": "#CDBD9644",

		"extensionButton.prominentBackground": "#D64E2C",
		"extensionButton.prominentForeground": "#CDBD96",
		"extensionButton.prominentHoverBackground": "#b35a6d",

		"gitDecoration.modifiedResourceForeground": "#CDBD96",
		"gitDecoration.deletedResourceForeground": "#D64E2C",
		"gitDecoration.untrackedResourceForeground": "#58A75E",
		"gitDecoration.ignoredResourceForeground": "#CDBD9644"
	},
	"tokenColors": [
		{
			"scope": "",
			"settings": {
				//"background": "#242627ff",
				"foreground": "#CDBD96ff"
			}
		},
		{
			"scope": "emphasis",
			"settings": {
				"fontStyle": "italic"
			}
		},
		{
			"scope": "strong",
			"settings": {
				"fontStyle": "bold"
			}
		},
		{
			"scope": [
				"constant.other",
				"entity.name.function",
				"markup.list",
				"meta",
				"storage.modifier.import",
				"storage.modifier.import.java",
				"storage.modifier.package",
				"storage.modifier.package.java",
				"support.type.property-name",
				"support.type.vendored.property-name",
				//"variable.other",
				"variable.other.object.property",
				"variable.parameter"
			],
			"settings": {
				"foreground": "#CDBD96"
			}
		},
		{
			"scope": "markup.bold",
			"settings": {
				"fontStyle": "bold",
				"foreground": "#CDBD96"
			}
		},
		{
			"scope": "markup.italic",
			"settings": {
				"fontStyle": "italic",
				"foreground": "#CDBD96"
			}
		},
		{
			"scope": [
				"constant.character",
				"constant.character.escape", //.cpp e.g: cout<<"dir **\\**";
				"entity.other.attribute-name.localname.cs",
				"keyword.control.ternary",
				"keyword.operator.arithmetic",
				"keyword.operator.logical",
				"keyword.codetag.notation",
				"keyword.operator.spread",
				"keyword.operator.at.batchfile",
				"keyword.operator.assignment",
				"markup.fenced_code", //.md e.g: **'''code'''**
				"meta.tag.block.any.html",
				"meta.tag.inline.any.html",
				"storage.type.function.arrow",
				"comment",
				"constant.character.escape.line-continuation",
				"entity.name.tag.localname.cs",
				"keyword.command.rem",
				"invalid.deprecated",
				"meta.brace",
				//"punctuation",
				"punctuation.separator",
				"punctuation.accessor",
				"punctuation.terminator",
				"punctuation.definition.block",
				"punctuation.definition.parameters",
				"punctuation.definition.binding-pattern",
				"punctuation.definition.tag",
				"punctuation.definition.tag.begin.html",
				"punctuation.definition.tag.end.html",
				"punctuation.definition.tag.html"
			],
			"settings": {
				"foreground": "#CDBD9666"
			}
		},
		{
			"scope": [
				"comment.block.documentation",
				"comment.block.triple-slash"
			],
			"settings": {
				"foreground": "#CDBD96AA",
				"fontStyle": "bold"
			}
		},
		{
			"scope": [
				"storage",
				"keyword.control.new",
				"keyword.operator.new",
				"variable.language.this",
				"variable.language.super",
				"support.class",
				"support.constant",
				"support.class.builtin",
				"support.constant.media" //.css e.g. @media **print**
			],
			"settings": {
				"fontStyle": "bold",
				"foreground": "#D64E2C"
			}
		},
		// {
		// 	"scope": [
		// 	],
		// 	"settings": {
		// 		"foreground": "#DD6E52" //"#bb546a"
		// 	}
		// },
		{
			"scope": [
				"keyword.control",
				"entity.other.attribute-name.pseudo-class.css", //.css e.g: audio:**not**([controls])
				"entity.other.attribute-name.pseudo-element.css",
				"entity.other.attribute-name.css", //.css e.g: audio:not([**controls**])
				"punctuation.definition.keyword", //.css e.g: **@**media print
				"string.quoted.docstring"
			],
			"settings": {
				"fontStyle": "",
				"foreground": "#F9B70E"
			}
		},
		{
			"scope": [
				//"keyword", //.cs e.g: **int** x
				"entity.name.tag",
				"entity.name.tag.css", //.css e.g: **h3**
				"keyword.declaration",
				"markup.heading", //.md e.g: ***HEADING***
				"storage.modifier",
				"storage.type", //.cpp e.g: **int** x
				"storage.type.primitive",
				"storage.type.primitive.java" //.jave e.g: **int** x
			],
			"settings": {
				"fontStyle": "",
				"foreground": "#E2812A"
			}
		},
		{
			"scope": [
				"entity.name.class",
				"entity.name.function.decorator",
				"entity.name.section.group-title.ini",
				//"entity.name.type",
				"entity.other.attribute-name.id.css",
				"entity.other.attribute-name",
				"entity.other.attribute-name.class.css",
				"entity.other.inherited-class",
				"keyword.operator.logical.python",
				"keyword.operator.sizeof",
				"markup",
				"string.other.link",
				"meta.class.body.java",
				//"meta.definition.variable",
				"meta.selector",
				"punctuation.definition.annotation",
				"punctuation.definition.storage.type.objc",
				"storage.type.annotation",
				"storage.type.annotation.java",
				"storage.type.cs",
				"storage.type.generic",
				"storage.type.generic.java",
				"storage.type.java",
				"storage.type.object",
				"storage.type.object.array.java",
				//"support.function",
				"support.type",
				"variable.language",
				"variable.other.java",
				"variable.other.readwrite.batchfile",
				"variable.parameter.function.language.special.self"
			],
			"settings": {
				"fontStyle": "",
				"foreground": "#F9B70E"
			}
		},
		{
			"scope": [
				"constant.language",
				"constant.numeric",
				"constant.other.color",
				"constant.other.color.rgb-value",
				"keyword.other.unit",
				"markup.inline.raw",
				"punctuation.definition.string.begin",
				"punctuation.definition.string.end",
				"source.ini",
				"string",
				"string.quoted.double.html",
				"storage.type.number",
				"storage.type.string",
				"support.constant.color",
				"support.constant.font-name",
				"support.constant.property-value",
				"entity.name.function.preprocessor",
				"invalid",
				"meta.preprocessor",
				"meta.preprocessor.macro",
				"string.unquoted.preprocessor",
				"variable.parameter.preprocessor"
			],
			"settings": {
				"foreground": "#58A75E"
			}
		},
		{
			"scope": [
				"constant.language.boolean.false",
				"constant.language.undefined",
				"constant.language.null"
			],
			"settings": {
				"fontStyle": "",
				"foreground": "#3C7140"
			}
		},
		{
			"scope": [
				"keyword.control.directive",
				"keyword.control.import",
				"keyword.other.import",
				"keyword.other.package",
				"keyword.other.special-method",
				"keyword.other.using",
				"keyword.preprocessor",
				"punctuation.definition.directive",
				"punctuation.separator.hash"
			],
			"settings": {
				"foreground": "#58A75E",
				"fontStyle": "bold"
			}
		},
		{
			"scope": [
				"constant.language.boolean.true"
			],
			"settings": {
				"foreground": "#76B77B",
				"fontStyle": ""
			}
		},
		{
			"scope": [
				"string.regexp",
				"meta.group.regexp",
				"punctuation.parenthesis.begin.regexp",
				"punctuation.parenthesis.end.regexp",
				"punctuation.parenthesis.non-capturing.begin.regexp",
				"punctuation.parenthesis.non-capturing.end.regexp",
				"constant.other.character-class.regexp",
				"keyword.operator.disjunction.regexp",
				"keyword.operator.quantifier.regexp"
			],
			"settings": {
				"foreground": "#76B77B",
				"fontStyle": "bold"
			}
		},
		{
			"scope": [
				"meta.tag.sgml.doctype",
				"punctuation.definition.block.tag.jsdoc",
				"meta.example.jsdoc",
				"storage.type.class.jsdoc"
			],
			"settings": {
				"fontStyle": "",
				"foreground": "#CDBD96AA"
			}
		}
	]
}